covtool/__init__.py
covtool/analysis.py
covtool/cli.py
covtool/core.py
covtool/drcov.py
covtool/inspector/__init__.py
covtool/inspector/dialogs.py
covtool/inspector/inspector.py
covtool/inspector/views.py
covtool/lift.py
covtool-0.4.4.dist-info/METADATA
covtool-0.4.4.dist-info/WHEEL
covtool-0.4.4.dist-info/entry_points.txt
covtool-0.4.4.dist-info/RECORD
