Metadata-Version: 2.3
Name: covtool
Version: 0.4.4
Summary: a multitool for manipulating coverage traces for dynamic analysis
Author: redthing1
Author-email: redthing1@alt.icu
Requires-Python: >=3.10,<4.0
Classifier: Programming Language :: Python :: 3
Classifier: Programming Language :: Python :: 3.10
Classifier: Programming Language :: Python :: 3.11
Classifier: Programming Language :: Python :: 3.12
Classifier: Programming Language :: Python :: 3.13
Requires-Dist: minlog (>=0.6.0,<0.7.0)
Requires-Dist: rich (>=13.0.0,<14.0.0)
Requires-Dist: typer (>=0.15.4,<0.16.0)
Requires-Dist: urwid (>=2.6.0,<3.0.0)
